gr1336_toolbox/__init__.py
gr1336_toolbox/files.py
gr1336_toolbox/misc.py
gr1336_toolbox/pathtools.py
gr1336_toolbox/phonemizer.py
gr1336_toolbox/text.py
gr1336_toolbox/types.py
gr1336_toolbox/backbones/misc/json_call_tools.py
gr1336_toolbox/backbones/texts/txt_requoter.py
gr1336_toolbox/backbones/texts/txt_splitter.py
gr1336_toolbox-0.7.4.dist-info/licenses/LICENSE
gr1336_toolbox-0.7.4.dist-info/METADATA
gr1336_toolbox-0.7.4.dist-info/WHEEL
gr1336_toolbox-0.7.4.dist-info/top_level.txt
gr1336_toolbox-0.7.4.dist-info/RECORD
