Metadata-Version: 2.4
Name: gr1336_toolbox
Version: 0.7.4
Summary: Personal collection of tools for any python projects. Currently in Pre-Alpha, many resources will be added, removed, and modified until everything aligns with most common needs.
Home-page: https://github.com/gr1336/gr1336_toolbox/
Author: gr1336
License: Apache Software License (Apache-2.0)
Classifier: Development Status :: 2 - Pre-Alpha
Classifier: Topic :: Software Development
Classifier: Topic :: Software Development :: Libraries
Classifier: Topic :: Software Development :: Testing
Classifier: Topic :: Software Development :: Pre-processors
Classifier: Topic :: Utilities
License-File: LICENSE
Requires-Dist: markdownify>=0.12.1
Requires-Dist: markdown2>=2.4.13
Requires-Dist: pyperclip>=1.8.2
Requires-Dist: textblob>=0.18.0
Requires-Dist: pyyaml>=6.0.0
Requires-Dist: nltk
Requires-Dist: scikit-learn>=1.4.0
Requires-Dist: gruut
Requires-Dist: num2words
Dynamic: author
Dynamic: classifier
Dynamic: description
Dynamic: description-content-type
Dynamic: home-page
Dynamic: license
Dynamic: license-file
Dynamic: requires-dist
Dynamic: summary
